{
  "screen": "Shop",
  "version": "v001",
  "stage": "5.0",
  "status": "reserved",
  "prototypeResolution": { "width": 1920, "height": 1080 },
  "assets": [
    { "name": "UI_Shop_Background_v001.png", "status": "pending", "node": "ShopBackground" },
    { "name": "UI_Shop_MerchantFrame_v001.png", "status": "pending", "node": "MerchantFrame" },
    { "name": "UI_Shop_ItemCardBase_v001.png", "status": "pending", "node": "ItemCardBase" },
    { "name": "UI_Shop_ButtonBuy_v001.png", "status": "pending", "node": "BuyButton" },
    { "name": "UI_Shop_ButtonReroll_v001.png", "status": "pending", "node": "RerollButton" },
    { "name": "UI_Shop_CurrencyPanel_v001.png", "status": "pending", "node": "CurrencyPanel" },
    { "name": "UI_Shop_ExitButton_v001.png", "status": "pending", "node": "ExitButton" }
  ]
}
